cppyml-0.7.0.data/purelib/cppyml/__init__.py
cppyml-0.7.0.data/purelib/cppyml/cppyml.pyd
cppyml-0.7.0.data/purelib/cppyml/utils.py
cppyml-0.7.0.data/purelib/tests/__init__.py
cppyml-0.7.0.data/purelib/tests/test_clustering.py
cppyml-0.7.0.data/purelib/tests/test_decision_trees.py
cppyml-0.7.0.data/purelib/tests/test_linear_regression.py
cppyml-0.7.0.data/purelib/tests/test_logistic_regression.py
cppyml-0.7.0.data/purelib/tests/test_utils.py
cppyml-0.7.0.dist-info/METADATA
cppyml-0.7.0.dist-info/WHEEL
cppyml-0.7.0.dist-info/top_level.txt
cppyml-0.7.0.dist-info/RECORD
