Metadata-Version: 2.1
Name: cppyml
Version: 0.7.0
Summary: Efficient implementations of selected ML algorithms for Python.
Home-page: https://romanwerpachowski.github.io/ML/
Author: Roman Werpachowski
Author-email: roman.werpachowski@gmail.com
License: GPL-3.0
Keywords: machine-learning ML extension algorithms numerical optimised
Platform: UNKNOWN
